Workbook

Sheet Calendar
A1: 30 Day Content Calendar
A2: 12 October to 10 November 2026. Topics come from the Daily Plan tab, so edits there show here automatically.
A4: Monday | B4: Tuesday | C4: Wednesday | D4: Thursday | E4: Friday | F4: Saturday | G4: Sunday
A5: 46307 | B5: 46308 | C5: 46309 | D5: 46310 | E5: 46311 | F5: 46312 | G5: 46313
A6: =IFERROR(INDEX('Daily Plan'!$F$6:$F$35,MATCH(A5,'Daily Plan'!$B$6:$B$35,0)),"") | B6: =IFERROR(INDEX('Daily Plan'!$F$6:$F$35,MATCH(B5,'Daily Plan'!$B$6:$B$35,0)),"") | C6: =IFERROR(INDEX('Daily Plan'!$F$6:$F$35,MATCH(C5,'Daily Plan'!$B$6:$B$35,0)),"") | D6: =IFERROR(INDEX('Daily Plan'!$F$6:$F$35,MATCH(D5,'Daily Plan'!$B$6:$B$35,0)),"") | E6: =IFERROR(INDEX('Daily Plan'!$F$6:$F$35,MATCH(E5,'Daily Plan'!$B$6:$B$35,0)),"") | F6: =IFERROR(INDEX('Daily Plan'!$F$6:$F$35,MATCH(F5,'Daily Plan'!$B$6:$B$35,0)),"") | G6: =IFERROR(INDEX('Daily Plan'!$F$6:$F$35,MATCH(G5,'Daily Plan'!$B$6:$B$35,0)),"")
A7: =IFERROR(INDEX('Daily Plan'!$G$6:$G$35,MATCH(A5,'Daily Plan'!$B$6:$B$35,0)),"") | B7: =IFERROR(INDEX('Daily Plan'!$G$6:$G$35,MATCH(B5,'Daily Plan'!$B$6:$B$35,0)),"") | C7: =IFERROR(INDEX('Daily Plan'!$G$6:$G$35,MATCH(C5,'Daily Plan'!$B$6:$B$35,0)),"") | D7: =IFERROR(INDEX('Daily Plan'!$G$6:$G$35,MATCH(D5,'Daily Plan'!$B$6:$B$35,0)),"") | E7: =IFERROR(INDEX('Daily Plan'!$G$6:$G$35,MATCH(E5,'Daily Plan'!$B$6:$B$35,0)),"") | F7: =IFERROR(INDEX('Daily Plan'!$G$6:$G$35,MATCH(F5,'Daily Plan'!$B$6:$B$35,0)),"") | G7: =IFERROR(INDEX('Daily Plan'!$G$6:$G$35,MATCH(G5,'Daily Plan'!$B$6:$B$35,0)),"")
A8: =IFERROR(INDEX('Daily Plan'!$E$6:$E$35,MATCH(A5,'Daily Plan'!$B$6:$B$35,0)),"") | B8: =IFERROR(INDEX('Daily Plan'!$E$6:$E$35,MATCH(B5,'Daily Plan'!$B$6:$B$35,0)),"") | C8: =IFERROR(INDEX('Daily Plan'!$E$6:$E$35,MATCH(C5,'Daily Plan'!$B$6:$B$35,0)),"") | D8: =IFERROR(INDEX('Daily Plan'!$E$6:$E$35,MATCH(D5,'Daily Plan'!$B$6:$B$35,0)),"") | E8: =IFERROR(INDEX('Daily Plan'!$E$6:$E$35,MATCH(E5,'Daily Plan'!$B$6:$B$35,0)),"") | F8: =IFERROR(INDEX('Daily Plan'!$E$6:$E$35,MATCH(F5,'Daily Plan'!$B$6:$B$35,0)),"") | G8: =IFERROR(INDEX('Daily Plan'!$E$6:$E$35,MATCH(G5,'Daily Plan'!$B$6:$B$35,0)),"")
A9: 46314 | B9: 46315 | C9: 46316 | D9: 46317 | E9: 46318 | F9: 46319 | G9: 46320
A10: =IFERROR(INDEX('Daily Plan'!$F$6:$F$35,MATCH(A9,'Daily Plan'!$B$6:$B$35,0)),"") | B10: =IFERROR(INDEX('Daily Plan'!$F$6:$F$35,MATCH(B9,'Daily Plan'!$B$6:$B$35,0)),"") | C10: =IFERROR(INDEX('Daily Plan'!$F$6:$F$35,MATCH(C9,'Daily Plan'!$B$6:$B$35,0)),"") | D10: =IFERROR(INDEX('Daily Plan'!$F$6:$F$35,MATCH(D9,'Daily Plan'!$B$6:$B$35,0)),"") | E10: =IFERROR(INDEX('Daily Plan'!$F$6:$F$35,MATCH(E9,'Daily Plan'!$B$6:$B$35,0)),"") | F10: =IFERROR(INDEX('Daily Plan'!$F$6:$F$35,MATCH(F9,'Daily Plan'!$B$6:$B$35,0)),"") | G10: =IFERROR(INDEX('Daily Plan'!$F$6:$F$35,MATCH(G9,'Daily Plan'!$B$6:$B$35,0)),"")
A11: =IFERROR(INDEX('Daily Plan'!$G$6:$G$35,MATCH(A9,'Daily Plan'!$B$6:$B$35,0)),"") | B11: =IFERROR(INDEX('Daily Plan'!$G$6:$G$35,MATCH(B9,'Daily Plan'!$B$6:$B$35,0)),"") | C11: =IFERROR(INDEX('Daily Plan'!$G$6:$G$35,MATCH(C9,'Daily Plan'!$B$6:$B$35,0)),"") | D11: =IFERROR(INDEX('Daily Plan'!$G$6:$G$35,MATCH(D9,'Daily Plan'!$B$6:$B$35,0)),"") | E11: =IFERROR(INDEX('Daily Plan'!$G$6:$G$35,MATCH(E9,'Daily Plan'!$B$6:$B$35,0)),"") | F11: =IFERROR(INDEX('Daily Plan'!$G$6:$G$35,MATCH(F9,'Daily Plan'!$B$6:$B$35,0)),"") | G11: =IFERROR(INDEX('Daily Plan'!$G$6:$G$35,MATCH(G9,'Daily Plan'!$B$6:$B$35,0)),"")
A12: =IFERROR(INDEX('Daily Plan'!$E$6:$E$35,MATCH(A9,'Daily Plan'!$B$6:$B$35,0)),"") | B12: =IFERROR(INDEX('Daily Plan'!$E$6:$E$35,MATCH(B9,'Daily Plan'!$B$6:$B$35,0)),"") | C12: =IFERROR(INDEX('Daily Plan'!$E$6:$E$35,MATCH(C9,'Daily Plan'!$B$6:$B$35,0)),"") | D12: =IFERROR(INDEX('Daily Plan'!$E$6:$E$35,MATCH(D9,'Daily Plan'!$B$6:$B$35,0)),"") | E12: =IFERROR(INDEX('Daily Plan'!$E$6:$E$35,MATCH(E9,'Daily Plan'!$B$6:$B$35,0)),"") | F12: =IFERROR(INDEX('Daily Plan'!$E$6:$E$35,MATCH(F9,'Daily Plan'!$B$6:$B$35,0)),"") | G12: =IFERROR(INDEX('Daily Plan'!$E$6:$E$35,MATCH(G9,'Daily Plan'!$B$6:$B$35,0)),"")
A13: 46321 | B13: 46322 | C13: 46323 | D13: 46324 | E13: 46325 | F13: 46326 | G13: 46327
A14: =IFERROR(INDEX('Daily Plan'!$F$6:$F$35,MATCH(A13,'Daily Plan'!$B$6:$B$35,0)),"") | B14: =IFERROR(INDEX('Daily Plan'!$F$6:$F$35,MATCH(B13,'Daily Plan'!$B$6:$B$35,0)),"") | C14: =IFERROR(INDEX('Daily Plan'!$F$6:$F$35,MATCH(C13,'Daily Plan'!$B$6:$B$35,0)),"") | D14: =IFERROR(INDEX('Daily Plan'!$F$6:$F$35,MATCH(D13,'Daily Plan'!$B$6:$B$35,0)),"") | E14: =IFERROR(INDEX('Daily Plan'!$F$6:$F$35,MATCH(E13,'Daily Plan'!$B$6:$B$35,0)),"") | F14: =IFERROR(INDEX('Daily Plan'!$F$6:$F$35,MATCH(F13,'Daily Plan'!$B$6:$B$35,0)),"") | G14: =IFERROR(INDEX('Daily Plan'!$F$6:$F$35,MATCH(G13,'Daily Plan'!$B$6:$B$35,0)),"")
A15: =IFERROR(INDEX('Daily Plan'!$G$6:$G$35,MATCH(A13,'Daily Plan'!$B$6:$B$35,0)),"") | B15: =IFERROR(INDEX('Daily Plan'!$G$6:$G$35,MATCH(B13,'Daily Plan'!$B$6:$B$35,0)),"") | C15: =IFERROR(INDEX('Daily Plan'!$G$6:$G$35,MATCH(C13,'Daily Plan'!$B$6:$B$35,0)),"") | D15: =IFERROR(INDEX('Daily Plan'!$G$6:$G$35,MATCH(D13,'Daily Plan'!$B$6:$B$35,0)),"") | E15: =IFERROR(INDEX('Daily Plan'!$G$6:$G$35,MATCH(E13,'Daily Plan'!$B$6:$B$35,0)),"") | F15: =IFERROR(INDEX('Daily Plan'!$G$6:$G$35,MATCH(F13,'Daily Plan'!$B$6:$B$35,0)),"") | G15: =IFERROR(INDEX('Daily Plan'!$G$6:$G$35,MATCH(G13,'Daily Plan'!$B$6:$B$35,0)),"")
A16: =IFERROR(INDEX('Daily Plan'!$E$6:$E$35,MATCH(A13,'Daily Plan'!$B$6:$B$35,0)),"") | B16: =IFERROR(INDEX('Daily Plan'!$E$6:$E$35,MATCH(B13,'Daily Plan'!$B$6:$B$35,0)),"") | C16: =IFERROR(INDEX('Daily Plan'!$E$6:$E$35,MATCH(C13,'Daily Plan'!$B$6:$B$35,0)),"") | D16: =IFERROR(INDEX('Daily Plan'!$E$6:$E$35,MATCH(D13,'Daily Plan'!$B$6:$B$35,0)),"") | E16: =IFERROR(INDEX('Daily Plan'!$E$6:$E$35,MATCH(E13,'Daily Plan'!$B$6:$B$35,0)),"") | F16: =IFERROR(INDEX('Daily Plan'!$E$6:$E$35,MATCH(F13,'Daily Plan'!$B$6:$B$35,0)),"") | G16: =IFERROR(INDEX('Daily Plan'!$E$6:$E$35,MATCH(G13,'Daily Plan'!$B$6:$B$35,0)),"")
A17: 46328 | B17: 46329 | C17: 46330 | D17: 46331 | E17: 46332 | F17: 46333 | G17: 46334
A18: =IFERROR(INDEX('Daily Plan'!$F$6:$F$35,MATCH(A17,'Daily Plan'!$B$6:$B$35,0)),"") | B18: =IFERROR(INDEX('Daily Plan'!$F$6:$F$35,MATCH(B17,'Daily Plan'!$B$6:$B$35,0)),"") | C18: =IFERROR(INDEX('Daily Plan'!$F$6:$F$35,MATCH(C17,'Daily Plan'!$B$6:$B$35,0)),"") | D18: =IFERROR(INDEX('Daily Plan'!$F$6:$F$35,MATCH(D17,'Daily Plan'!$B$6:$B$35,0)),"") | E18: =IFERROR(INDEX('Daily Plan'!$F$6:$F$35,MATCH(E17,'Daily Plan'!$B$6:$B$35,0)),"") | F18: =IFERROR(INDEX('Daily Plan'!$F$6:$F$35,MATCH(F17,'Daily Plan'!$B$6:$B$35,0)),"") | G18: =IFERROR(INDEX('Daily Plan'!$F$6:$F$35,MATCH(G17,'Daily Plan'!$B$6:$B$35,0)),"")
A19: =IFERROR(INDEX('Daily Plan'!$G$6:$G$35,MATCH(A17,'Daily Plan'!$B$6:$B$35,0)),"") | B19: =IFERROR(INDEX('Daily Plan'!$G$6:$G$35,MATCH(B17,'Daily Plan'!$B$6:$B$35,0)),"") | C19: =IFERROR(INDEX('Daily Plan'!$G$6:$G$35,MATCH(C17,'Daily Plan'!$B$6:$B$35,0)),"") | D19: =IFERROR(INDEX('Daily Plan'!$G$6:$G$35,MATCH(D17,'Daily Plan'!$B$6:$B$35,0)),"") | E19: =IFERROR(INDEX('Daily Plan'!$G$6:$G$35,MATCH(E17,'Daily Plan'!$B$6:$B$35,0)),"") | F19: =IFERROR(INDEX('Daily Plan'!$G$6:$G$35,MATCH(F17,'Daily Plan'!$B$6:$B$35,0)),"") | G19: =IFERROR(INDEX('Daily Plan'!$G$6:$G$35,MATCH(G17,'Daily Plan'!$B$6:$B$35,0)),"")
A20: =IFERROR(INDEX('Daily Plan'!$E$6:$E$35,MATCH(A17,'Daily Plan'!$B$6:$B$35,0)),"") | B20: =IFERROR(INDEX('Daily Plan'!$E$6:$E$35,MATCH(B17,'Daily Plan'!$B$6:$B$35,0)),"") | C20: =IFERROR(INDEX('Daily Plan'!$E$6:$E$35,MATCH(C17,'Daily Plan'!$B$6:$B$35,0)),"") | D20: =IFERROR(INDEX('Daily Plan'!$E$6:$E$35,MATCH(D17,'Daily Plan'!$B$6:$B$35,0)),"") | E20: =IFERROR(INDEX('Daily Plan'!$E$6:$E$35,MATCH(E17,'Daily Plan'!$B$6:$B$35,0)),"") | F20: =IFERROR(INDEX('Daily Plan'!$E$6:$E$35,MATCH(F17,'Daily Plan'!$B$6:$B$35,0)),"") | G20: =IFERROR(INDEX('Daily Plan'!$E$6:$E$35,MATCH(G17,'Daily Plan'!$B$6:$B$35,0)),"")
A21: 46335 | B21: 46336 | C21: 46337 | D21: 46338 | E21: 46339 | F21: 46340 | G21: 46341
A22: =IFERROR(INDEX('Daily Plan'!$F$6:$F$35,MATCH(A21,'Daily Plan'!$B$6:$B$35,0)),"") | B22: =IFERROR(INDEX('Daily Plan'!$F$6:$F$35,MATCH(B21,'Daily Plan'!$B$6:$B$35,0)),"") | C22: =IFERROR(INDEX('Daily Plan'!$F$6:$F$35,MATCH(C21,'Daily Plan'!$B$6:$B$35,0)),"") | D22: =IFERROR(INDEX('Daily Plan'!$F$6:$F$35,MATCH(D21,'Daily Plan'!$B$6:$B$35,0)),"") | E22: =IFERROR(INDEX('Daily Plan'!$F$6:$F$35,MATCH(E21,'Daily Plan'!$B$6:$B$35,0)),"") | F22: =IFERROR(INDEX('Daily Plan'!$F$6:$F$35,MATCH(F21,'Daily Plan'!$B$6:$B$35,0)),"") | G22: =IFERROR(INDEX('Daily Plan'!$F$6:$F$35,MATCH(G21,'Daily Plan'!$B$6:$B$35,0)),"")
A23: =IFERROR(INDEX('Daily Plan'!$G$6:$G$35,MATCH(A21,'Daily Plan'!$B$6:$B$35,0)),"") | B23: =IFERROR(INDEX('Daily Plan'!$G$6:$G$35,MATCH(B21,'Daily Plan'!$B$6:$B$35,0)),"") | C23: =IFERROR(INDEX('Daily Plan'!$G$6:$G$35,MATCH(C21,'Daily Plan'!$B$6:$B$35,0)),"") | D23: =IFERROR(INDEX('Daily Plan'!$G$6:$G$35,MATCH(D21,'Daily Plan'!$B$6:$B$35,0)),"") | E23: =IFERROR(INDEX('Daily Plan'!$G$6:$G$35,MATCH(E21,'Daily Plan'!$B$6:$B$35,0)),"") | F23: =IFERROR(INDEX('Daily Plan'!$G$6:$G$35,MATCH(F21,'Daily Plan'!$B$6:$B$35,0)),"") | G23: =IFERROR(INDEX('Daily Plan'!$G$6:$G$35,MATCH(G21,'Daily Plan'!$B$6:$B$35,0)),"")
A24: =IFERROR(INDEX('Daily Plan'!$E$6:$E$35,MATCH(A21,'Daily Plan'!$B$6:$B$35,0)),"") | B24: =IFERROR(INDEX('Daily Plan'!$E$6:$E$35,MATCH(B21,'Daily Plan'!$B$6:$B$35,0)),"") | C24: =IFERROR(INDEX('Daily Plan'!$E$6:$E$35,MATCH(C21,'Daily Plan'!$B$6:$B$35,0)),"") | D24: =IFERROR(INDEX('Daily Plan'!$E$6:$E$35,MATCH(D21,'Daily Plan'!$B$6:$B$35,0)),"") | E24: =IFERROR(INDEX('Daily Plan'!$E$6:$E$35,MATCH(E21,'Daily Plan'!$B$6:$B$35,0)),"") | F24: =IFERROR(INDEX('Daily Plan'!$E$6:$E$35,MATCH(F21,'Daily Plan'!$B$6:$B$35,0)),"") | G24: =IFERROR(INDEX('Daily Plan'!$E$6:$E$35,MATCH(G21,'Daily Plan'!$B$6:$B$35,0)),"")
A26: Week themes
A27: Week 1: Speed and security (12 to 18 Oct)
A28: Week 2: AI search (19 to 25 Oct)
A29: Week 3: Spam update, local and Halloween (26 Oct to 1 Nov)
A30: Week 4: Black Friday prep (2 to 8 Nov)
A31: Wrap up and countdown (9 to 10 Nov)
A33: Key dates ahead: Halloween 31 Oct, US clocks change 1 Nov, Thanksgiving 26 Nov, Black Friday 27 Nov, Small Business Saturday 28 Nov, Cyber Monday 30 Nov.

Sheet Daily Plan
A1: Vyntic Studio: 30 Day Social Media Plan
A2: Monday 12 October to Tuesday 10 November 2026. One main post a day, built on topics trending now. Yellow columns are yours to update.
A3: Posts planned | C3: Scheduled | E3: Published | G3: Still to do
A4: =COUNTA(F6:F35) | C4: =COUNTIF(P6:P35,"Scheduled") | E4: =COUNTIF(P6:P35,"Published") | G4: =COUNTIF(P6:P35,"To do")+COUNTIF(P6:P35,"In progress")
A5: Day | B5: Date | C5: Weekday | D5: Week theme | E5: Pillar | F5: Topic | G5: Format | H5: Platforms | I5: Hook (first line) | J5: Key points | K5: Trending keywords | L5: Hashtags | M5: Call to action | N5: Asset to create | O5: Link | P5: Status | Q5: Notes
A6: 1 | B6: 46307 | C6: Monday | D6: Week 1: Speed and security | E6: Product | F6: Free WordPress speed plugin launch | G6: Reel (ready) | H6: Instagram Reels, Facebook, TikTok, YouTube Shorts, LinkedIn | I6: Your WordPress site scores 31 on mobile? | J6: Show the 31 to 98 jump, the four features, free with no account or API key. | K6: WordPress speed optimization, Core Web Vitals, PageSpeed Insights | L6: #wordpress #pagespeed #corewebvitals #websitespeed #wordpressplugin | M6: Comment SPEED for the link | N6: vyntic-reel-speed-optimizer.mp4 | O6: https://vyntic.studio/plugins/vyntic-speed-optimizer/ | P6: To do
A7: 2 | B7: 46308 | C7: Tuesday | D7: Week 1: Speed and security | E7: News | F7: WordPress 7.1.3 security release: update now | G7: Single image + text | H7: LinkedIn, Facebook, X, Google Business Profile | I7: WordPress fixed 7 security holes on October 6. Is your site updated? | J7: 7 security fixes and 4 bug fixes. Safe update steps: backup, update on staging, update plugins, test forms and checkout. | K7: WordPress 7.1.3, WordPress security update | L7: #wordpress #wordpresssecurity #websitesecurity #smallbusiness | M7: DM us UPDATE and we will check your site | N7: News graphic: '7.1.3 is out. Update today.' | O7: https://wordpress.org/news/2026/10/wordpress-7-1-3-maintenance-and-security-release/ | P7: To do
A8: 3 | B8: 46309 | C8: Wednesday | D8: Week 1: Speed and security | E8: Educate | F8: Why is your WordPress site slow? 5 fixes | G8: Carousel (ready) | H8: Instagram, Facebook, LinkedIn (PDF) | I8: 5 problems we fix on almost every WordPress site | J8: Scripts, no cache, heavy images, render-blocking CSS and fonts, nobody checks the score. | K8: website speed, Core Web Vitals, Total Blocking Time | L8: #wordpresstips #pagespeed #corewebvitals #seo #webdesign | M8: Save this post | N8: vyntic-carousel-speed.zip / .pdf | O8: https://vyntic.studio/plugins/ | P8: To do
A9: 4 | B9: 46310 | C9: Thursday | D9: Week 1: Speed and security | E9: Proof | F9: Before and after: real client PageSpeed result | G9: Single image | H9: Instagram, Facebook, LinkedIn, Google Business Profile | I9: From 31 to 98 on mobile. Here is what we changed. | J9: Use a real client screenshot. List the 3 changes that made the biggest difference. | K9: PageSpeed score, LCP, website speed | L9: #casestudy #pagespeed #webdesign #wordpress | M9: Want the same? Book a free call | N9: vyntic-post-speed-optimizer.png (swap in real numbers) | O9: https://vyntic.studio/services/website-speed-optimization/ | P9: To do
A10: 5 | B10: 46311 | C10: Friday | D10: Week 1: Speed and security | E10: Educate | F10: What is LCP? Explained in 30 seconds | G10: Talking head video (30 s) | H10: Instagram Reels, TikTok, YouTube Shorts, LinkedIn | I10: Google is timing how fast your biggest image loads. | J10: LCP = time until the main content shows. Good is under 2.5 s. Top 3 fixes: compress hero image, preload it, use a page cache. | K10: Largest Contentful Paint, LCP, Core Web Vitals | L10: #corewebvitals #seo #websitespeed #wordpresstips | M10: Read the full guide (link in bio) | N10: Phone video, captions on | O10: https://vyntic.studio/core-web-vitals-explained/ | P10: To do
A11: 6 | B11: 46312 | C11: Saturday | D11: Week 1: Speed and security | E11: Behind the scenes | F11: How we build a website in 4 weeks | G11: Stories (5 frames) | H11: Instagram Stories, Facebook Stories | I11: A website in 4 weeks? Here is our real process. | J11: Week 1 plan and content, week 2 design, week 3 build, week 4 test, speed and launch. | K11: web design process, website redesign | L11: #webdesign #behindthescenes #agencylife | M11: Reply to this story with your questions | N11: Screens from Figma and WordPress | O11: https://vyntic.studio/services/web-design/ | P11: To do
A12: 7 | B12: 46313 | C12: Sunday | D12: Week 1: Speed and security | E12: Engage | F12: Poll: what slows your site the most? | G12: Poll | H12: Instagram Stories, LinkedIn, X | I12: Be honest: what is slowing your website down? | J12: Options: plugins, images, hosting, no idea. Share results on Monday. | K12: website speed | L12: #wordpress #webdesign | M12: Vote | N12: Poll sticker | P12: To do
A13: 8 | B13: 46314 | C13: Monday | D13: Week 2: AI search | E13: Educate | F13: AI Overviews are taking your clicks. What to do now | G13: Carousel (6 slides) | H13: Instagram, LinkedIn (PDF), Facebook | I13: Ranking number 1 is not enough anymore. | J13: Ahrefs: position 1 CTR is about 34.5% lower when an AI Overview shows. Answer questions directly, add FAQ and schema, build brand mentions, track AI traffic. | K13: AI Overviews, AI Mode, zero click search | L13: #seo #aioverviews #aisearch #googleseo #digitalmarketing | M13: Save and share with your marketing team | N13: 6 slide carousel | O13: https://vyntic.studio/services/ai-search-visibility/ | P13: To do
A14: 9 | B14: 46315 | C14: Tuesday | D14: Week 2: AI search | E14: News | F14: Search Console now shows AI performance: how to read it | G14: Screen recording (45 s) | H14: LinkedIn, YouTube Shorts, X | I14: Google finally shows how you perform in AI search. Here is where to find it. | J14: Generative AI performance reports are rolled out to all sites. Show where it lives, what to look at, what to do with it. | K14: Search Console AI report, generative AI performance | L14: #seo #googlesearchconsole #aisearch | M14: Follow for weekly SEO updates | N14: Screen recording of Search Console | O14: https://www.seroundtable.com/october-2026-google-webmaster-report-42185.html | P14: To do
A15: 10 | B15: 46316 | C15: Wednesday | D15: Week 2: AI search | E15: Educate | F15: How to get your business recommended by ChatGPT | G15: Reel (3 steps) | H15: Instagram Reels, TikTok, YouTube Shorts, LinkedIn | I15: Ask ChatGPT for the best dentist in your city. Are you in the answer? | J15: 1. Clear service pages that answer questions. 2. Reviews and mentions on trusted sites. 3. Consistent business info everywhere. | K15: GEO, generative engine optimization, ChatGPT recommendations, AI search visibility | L15: #aisearch #chatgpt #seo #localbusiness #marketingtips | M15: Comment AI for our checklist | N15: vyntic.studio blog graphic + screen | O15: https://vyntic.studio/get-recommended-by-chatgpt/ | P15: To do
A16: 11 | B16: 46317 | C16: Thursday | D16: Week 2: AI search | E16: Educate | F16: SEO vs GEO: what actually changed in 2026 | G16: Text post | H16: LinkedIn, X thread | I16: Everyone says SEO is dead. Our client data says something else. | J16: Traditional SEO still brings the high intent traffic. GEO adds: answer-first content, entities, citations, brand mentions. Do both. | K16: GEO, AEO, answer engine optimization, SEO 2026 | L16: #seo #geo #aeo #marketing | M16: What are you seeing? Comment below | N16: Text only (LinkedIn favours it) | O16: https://vyntic.studio/services/seo-services/ | P16: To do
A17: 12 | B17: 46318 | C17: Friday | D17: Week 2: AI search | E17: News | F17: WordPress and AI agents: the new MCP Adapter in plain English | G17: Single image + text | H17: LinkedIn, X, Facebook | I17: AI assistants can now work with WordPress sites in a standard way. | J17: What MCP is in one sentence, what the canonical WordPress MCP Adapter does, what it means for site owners (and what to be careful with). | K17: WordPress MCP, AI agents WordPress, WordPress AI | L17: #wordpress #ai #mcp #webdevelopment | M17: Follow for WordPress news without the jargon | N17: Simple diagram: AI app to MCP to WordPress | O17: https://www.searchenginejournal.com/category/cms/wp/ | P17: To do
A18: 13 | B18: 46319 | C18: Saturday | D18: Week 2: AI search | E18: Proof | F18: Client review spotlight | G18: Quote graphic | H18: Instagram, Facebook, Google Business Profile, LinkedIn | I18: 'They made our site twice as fast and leads doubled.' | J18: Use a real Google review, with the client's permission. Add the project result in one line. | K18: web design reviews, WordPress agency | L18: #clientlove #testimonial #webdesign | M18: Read more reviews on Google | N18: Review quote card in brand colours | O18: https://vyntic.studio | P18: To do
A19: 14 | B19: 46320 | C19: Sunday | D19: Week 2: AI search | E19: Engage | F19: Ask me anything: AI search and SEO | G19: Q&A stickers / thread | H19: Instagram Stories, X, LinkedIn comments | I19: Ask me anything about AI search this weekend. | J19: Answer 5 to 8 questions with short replies. Turn the best ones into posts next week. | K19: AI search, SEO questions | L19: #seo #aisearch #askmeanything | M19: Send your question | N19: Question sticker | P19: To do
A20: 15 | B20: 46321 | C20: Monday | D20: Week 3: Spam update, local and Halloween | E20: News | F20: The September spam update just finished: 5 things that get sites hit | G20: Carousel (6 slides) | H20: Instagram, LinkedIn (PDF), Facebook | I20: Google's latest spam update finished on October 8. Is your site safe? | J20: Scaled AI content with no value, expired domain abuse, hidden links, doorway pages, cloaking. What to do if traffic dropped. | K20: Google spam update, spam policies, traffic drop | L20: #seo #googleupdate #googleseo #digitalmarketing | M20: Traffic dropped? DM us AUDIT | N20: 6 slide carousel | O20: https://seroundtable.com/google-september-2026-spam-update-done-42235.html | P20: To do
A21: 16 | B21: 46322 | C21: Tuesday | D21: Week 3: Spam update, local and Halloween | E21: Educate | F21: 7 Google Business Profile fixes in 10 minutes | G21: Carousel (8 slides) | H21: Instagram, Facebook, LinkedIn, Google Business Profile | I21: Your Google Business Profile is your new homepage. | J21: Primary category, services, photos every week, Q and A, posts, review replies, correct hours. | K21: Google Business Profile optimization, local SEO, Google Maps ranking | L21: #localseo #googlebusinessprofile #smallbusiness #googlemaps | M21: Save this checklist | N21: 8 slide carousel | O21: https://vyntic.studio/google-business-profile-guide/ | P21: To do
A22: 17 | B22: 46323 | C22: Wednesday | D22: Week 3: Spam update, local and Halloween | E22: Engage | F22: Website horror story #1: the 12 second homepage | G22: Reel (Halloween) | H22: Instagram Reels, TikTok, YouTube Shorts, Facebook | I22: This homepage took 12 seconds to load. Here is what we found. | J22: Spooky music, reveal: 8 MB slider, 47 plugins, no cache. End with the after score. | K22: website horror stories, slow website | L22: #halloween #websitefails #webdesign #wordpress | M22: Tag someone whose site is this slow | N22: Screen recording + spooky text | P22: To do
A23: 18 | B23: 46324 | C23: Thursday | D23: Week 3: Spam update, local and Halloween | E23: Behind the scenes | F23: The scariest plugin list we have ever seen | G23: Meme / single image | H23: Instagram, Facebook, X, LinkedIn | I23: 47 plugins. 3 page builders. 0 backups. | J23: Light humour, then 3 tips: remove unused plugins, one builder, daily backups. | K23: WordPress plugins, website maintenance | L23: #halloween #wordpress #webdevhumor | M23: Comment your plugin count | N23: Meme image in brand style | P23: To do
A24: 19 | B24: 46325 | C24: Friday | D24: Week 3: Spam update, local and Halloween | E24: Educate | F24: Clocks change Nov 1: update your Google hours and holiday hours | G24: Single image + GBP post | H24: Google Business Profile, Facebook, Instagram Stories | I24: Wrong hours on Google = lost customers. | J24: US daylight saving time ends Sunday November 1. Add holiday hours for Thanksgiving, Black Friday and Christmas now. | K24: Google Business Profile holiday hours, local SEO | L24: #localseo #smallbusiness #googlebusinessprofile | M24: Need help? Message us | N24: Reminder graphic | O24: https://vyntic.studio/services/google-business-profile-optimization/ | P24: To do
A25: 20 | B25: 46326 | C25: Saturday | D25: Week 3: Spam update, local and Halloween | E25: Offer | F25: Trick or treat: free speed check for the first 10 comments | G25: Single image | H25: Instagram, Facebook, LinkedIn, X | I25: Trick or treat? We will check your site speed for free. | J25: First 10 people who comment their URL get a short PageSpeed review in a video reply. | K25: free website audit, PageSpeed | L25: #halloween #freeaudit #websitespeed #smallbusiness | M25: Comment your website URL | N25: Halloween graphic in brand colours | O25: https://vyntic.studio/contact/ | P25: To do
A26: 21 | B26: 46327 | C26: Sunday | D26: Week 3: Spam update, local and Halloween | E26: Behind the scenes | F26: October recap: what we shipped | G26: Text post + photos | H26: LinkedIn, Facebook, Instagram carousel | I26: October at Vyntic in 30 seconds. | J26: Speed Optimizer 1.4.0 with weekly PageSpeed reports, new plugins page, client launches, numbers. | K26: agency update | L26: #buildinpublic #agencylife #wordpress | M26: Follow along for November | N26: 3 to 5 photos or screenshots | O26: https://vyntic.studio/plugins/ | P26: To do
A27: 22 | B27: 46328 | C27: Monday | D27: Week 4: Black Friday prep | E27: Educate | F27: Black Friday is November 27: website checklist (25 days out) | G27: Carousel (8 slides) | H27: Instagram, Facebook, LinkedIn (PDF), Pinterest | I27: Black Friday is 25 days away. Is your website ready? | J27: Speed test, mobile checkout, stock and prices, landing page, email capture, Google holiday hours, backup, load test. | K27: Black Friday 2026, BFCM, ecommerce website checklist | L27: #blackfriday #bfcm #ecommerce #smallbusiness #woocommerce | M27: Save this checklist | N27: 8 slide carousel | O27: https://www.klaviyo.com/uk/bfcm/calendar | P27: To do
A28: 23 | B28: 46329 | C28: Tuesday | D28: Week 4: Black Friday prep | E28: Educate | F28: Your checkout is losing sales: 3 speed fixes before Black Friday | G28: Reel | H28: Instagram Reels, TikTok, YouTube Shorts, LinkedIn | I28: Every extra second at checkout costs you sales. | J28: Fewer checkout fields, no heavy scripts on checkout, page cache everywhere except cart and checkout. | K28: WooCommerce speed, checkout optimization | L28: #woocommerce #ecommerce #blackfriday #websitespeed | M28: Comment CHECKOUT for our list | N28: Screen recording | O28: https://vyntic.studio/services/ecommerce-development/ | P28: To do
A29: 24 | B29: 46330 | C29: Wednesday | D29: Week 4: Black Friday prep | E29: Educate | F29: Shoppers now ask AI what to buy: get your products in the answer | G29: Carousel (6 slides) | H29: Instagram, LinkedIn (PDF), Facebook | I29: More shoppers skip Google and ask ChatGPT or AI Mode what to buy. | J29: Product schema, clear product descriptions, reviews on and off site, comparison and FAQ content, fast pages. | K29: AI shopping, AI Mode shopping, product schema | L29: #ecommerce #aisearch #blackfriday #seo | M29: Save for your Black Friday prep | N29: 6 slide carousel | O29: https://www.yotpo.com/blog/black-friday-marketing-strategy.md | P29: To do
A30: 25 | B30: 46331 | C30: Thursday | D30: Week 4: Black Friday prep | E30: Proof | F30: Case study: ecommerce redesign results | G30: Carousel (5 slides) | H30: Instagram, LinkedIn, Facebook | I30: How a redesign changed one store's results. | J30: Use a real client: problem, what we did, numbers (speed, conversion rate, revenue), quote. | K30: ecommerce website design, conversion rate | L30: #casestudy #ecommerce #webdesign | M30: Want results like this? Book a call | N30: 5 slide case study | O30: https://vyntic.studio/services/ecommerce-development/ | P30: To do
A31: 26 | B31: 46332 | C31: Friday | D31: Week 4: Black Friday prep | E31: Offer | F31: Black Friday landing page in 7 days | G31: Single image + text | H31: LinkedIn, Facebook, Instagram, Google Business Profile | I31: Need a Black Friday landing page? We build it in 7 days. | J31: What is included, deadline to book (Nov 13), one example. | K31: Black Friday landing page, landing page design | L31: #blackfriday #landingpage #webdesign #smallbusiness | M31: Book before November 13 | N31: Offer graphic | O31: https://vyntic.studio/services/landing-page-design/ | P31: To do
A32: 27 | B32: 46333 | C32: Saturday | D32: Week 4: Black Friday prep | E32: Educate | F32: Small Business Saturday is November 28: get found locally | G32: Single image + GBP post | H32: Google Business Profile, Facebook, Instagram | I32: Small Business Saturday is in 3 weeks. Will locals find you? | J32: Post your offer on Google Business Profile, update photos, ask 5 customers for reviews, add holiday hours. | K32: Small Business Saturday 2026, local SEO | L32: #smallbusinesssaturday #shoplocal #localseo #smallbusiness | M32: Share with a local business owner | N32: Reminder graphic | O32: https://vyntic.studio/services/local-seo/ | P32: To do
A33: 28 | B33: 46334 | C33: Sunday | D33: Week 4: Black Friday prep | E33: Engage | F33: Poll: are you running a Black Friday offer this year? | G33: Poll | H33: Instagram Stories, LinkedIn, X | I33: Quick one: Black Friday offer this year? | J33: Options: yes big sale, small discount, no, not sure. Share results with tips. | K33: Black Friday 2026 | L33: #blackfriday #smallbusiness | M33: Vote | N33: Poll sticker | P33: To do
A34: 29 | B34: 46335 | C34: Monday | D34: Wrap up and countdown | E34: Educate | F34: How much does a website cost in 2026? Real numbers | G34: Carousel (7 slides) | H34: Instagram, LinkedIn (PDF), Facebook, Pinterest | I34: Website prices from 500 to 50,000 dollars. Here is why. | J34: Price ranges by type, what drives cost, hidden costs, how to choose. | K34: website cost 2026, how much does a website cost | L34: #webdesign #smallbusiness #websitecost #wordpress | M34: Try our free cost calculator | N34: 7 slide carousel | O34: https://vyntic.studio/website-cost/ | P34: To do
A35: 30 | B35: 46336 | C35: Tuesday | D35: Wrap up and countdown | E35: Offer | F35: Early Black Friday offer + best of the month | G35: Reel or carousel | H35: All platforms | I35: Our Black Friday offer for small businesses starts now. | J35: Announce your real offer (fill in). Link the 3 best posts of the month. | K35: Black Friday web design deal | L35: #blackfriday #webdesign #smallbusiness #vynticstudio | M35: Book a call before spots are gone | N35: Offer graphic + reel | O35: https://vyntic.studio/contact/ | P35: To do

Sheet Trending Keywords
A1: Trending keywords and topics (checked 10 October 2026)
A2: Why each topic is hot right now, and where it is used in the plan. Recheck Google Trends before each week.
A4: Keyword / topic | B4: Category | C4: Why it is trending now | D4: Used on days | E4: Source
A5: WordPress 7.1.3 security update | B5: WordPress | C5: Released 6 October 2026 with 7 security fixes and 4 bug fixes. Site owners are searching how to update safely. | D5: 2 | E5: https://wordpress.org/news/2026/10/wordpress-7-1-3-maintenance-and-security-release/
A6: WordPress MCP / AI agents WordPress | B6: WordPress, AI | C6: WordPress released a canonical MCP Adapter that connects AI tools to sites. New and widely covered. | D6: 12 | E6: https://www.searchenginejournal.com/category/cms/wp/
A7: Core Web Vitals, LCP, PageSpeed Insights | B7: Speed | C7: Evergreen with steady demand. Ties directly to the free Speed Optimizer plugin. | D7: 1, 3, 4, 5 | E7: https://www.wordstream.com/blog/2026-seo-trends
A8: AI Overviews / AI Mode | B8: SEO | C8: AI Mode prompt box now appears inside some AI Overviews. Click loss is the top SEO worry (Ahrefs: position 1 CTR about 34.5% lower with an AI Overview). | D8: 8, 9 | E8: https://www.seroundtable.com/october-2026-google-webmaster-report-42185.html
A9: Search Console generative AI report | B9: SEO | C9: Generative AI performance reports have rolled out to all sites worldwide. Owners want to know how to read them. | D9: 9 | E9: https://www.seroundtable.com/october-2026-google-webmaster-report-42185.html
A10: Zero click search | B10: SEO | C10: Grows with AI answers. Useful framing for why websites need answer-first content. | D10: 8 | E10: https://www.evergreen.media/en/guide/seo-this-year/
A11: GEO / AEO (generative and answer engine optimization) | B11: SEO | C11: Named as a key 2026 trend next to traditional SEO, which still brings high intent traffic. | D11: 10, 11 | E11: https://www.wordstream.com/blog/2026-seo-trends
A12: Get recommended by ChatGPT / AI search visibility | B12: SEO | C12: Local businesses ask how to show up in ChatGPT and Gemini answers. Matches an existing Vyntic blog post. | D12: 10 | E12: https://www.position.digital/blog/ai-seo-news/
A13: Google spam update | B13: SEO | C13: September 2026 spam update finished rolling out on 8 October. Sites that dropped are searching for answers. | D13: 15 | E13: https://seroundtable.com/google-september-2026-spam-update-done-42235.html
A14: Google core update | B14: SEO | C14: Two core updates so far in 2026 (March, May). Always high interest; post fast if a new one starts. | D14: Watch | E14: https://searchengineland.com/google-may-2026-core-update-rolling-out-now-478430
A15: Google Business Profile optimization / holiday hours | B15: Local SEO | C15: Peak season for local search; holiday hours and the clock change on 1 November. | D15: 16, 19, 27 | E15: https://www.klaviyo.com/uk/bfcm/calendar
A16: Halloween website horror stories | B16: Seasonal | C16: Halloween 31 October. Light, shareable content that still teaches. | D16: 17, 18, 20
A17: Black Friday 2026 / BFCM | B17: Seasonal | C17: Black Friday is 27 November, Cyber Monday 30 November. Many shoppers research deals before mid November, so prep content in early November. | D17: 22 to 30 | E17: https://www.klaviyo.com/uk/bfcm/calendar
A18: AI shopping / product schema | B18: Ecommerce | C18: More buyers ask ChatGPT, Gemini or AI Mode what to buy (vendor reported, treat numbers with care). | D18: 24 | E18: https://www.yotpo.com/blog/black-friday-marketing-strategy.md
A19: Small Business Saturday 2026 | B19: Seasonal, local | C19: 28 November 2026. Good for local business audiences. | D19: 27 | E19: https://www.klaviyo.com/uk/bfcm/calendar
A20: Website cost 2026 | B20: Sales | C20: Evergreen high intent query, peaks before budgets are set for the new year. Matches the Vyntic cost calculator. | D20: 29 | E20: https://vyntic.studio/website-cost/
A21: WordPress accessibility | B21: WordPress | C21: WordPress Accessibility Day ran 7 to 8 October 2026. Good topic for a later post. | D21: Spare | E21: https://wpaccessibility.day/2026/

Sheet Weekly Routine
A1: How to use this plan
A2: 1 | B2: Each day has one main post. Make it once, then adapt it for every platform listed (crop, change the first line, adjust hashtags).
A3: 2 | B3: Change Status as you go. The counters on the Daily Plan and the Calendar update by themselves.
A4: 3 | B4: Days marked 'real client' need your own numbers or reviews. Never post made-up results.
A5: 4 | B5: If big news breaks (a Google core update, a WordPress release), swap it into the next free day. Speed matters more than polish.
A7: Weekly routine (about 5 hours)
A8: Monday | B8: Plan and batch: write captions for the week, design carousels and images (2 hours).
A9: Tuesday | B9: Record short videos for the week in one go (1 hour).
A10: Wednesday | B10: Schedule everything in Meta Business Suite (Instagram, Facebook) and LinkedIn (30 minutes).
A11: Every day | B11: 15 minutes replying to comments and DMs, 10 minutes commenting on 5 posts in your niche.
A12: Friday | B12: Check what worked: saves, shares, comments, link clicks. Note the winners (30 minutes).
A13: Sunday | B13: Two Google Business Profile posts for the week, ask for 2 reviews.
A15: Posting times to test
A16: Instagram and Facebook | B16: 7 to 9 pm local time on weekdays, late morning on weekends.
A17: LinkedIn | B17: Tuesday to Thursday, 8 to 10 am.
A18: TikTok and Shorts | B18: 6 to 10 pm.
A19: Google Business Profile | B19: Any time, twice a week.
A21: Content mix for the month
A22: Educate | B22: About 40%. Tips, how to, explainers.
A23: News | B23: About 15%. WordPress and Google updates, posted fast.
A24: Proof | B24: About 15%. Case studies, reviews, before and after.
A25: Product and Offer | B25: About 15%. Free plugins, services, Black Friday offer.
A26: Engage and Behind the scenes | B26: About 15%. Polls, Q and A, process, team.
